vinparse/__init__.py
vinparse/vinparse.py
vinparse-0.1.dist-info/METADATA
vinparse-0.1.dist-info/WHEEL
vinparse-0.1.dist-info/top_level.txt
vinparse-0.1.dist-info/RECORD
