Metadata-Version: 2.4
Name: vinparse
Version: 0.1
Summary: A library for decoding Vehicle Identification Numbers (VIN)
Author-email: relyadev <relyadev@gmail.com>
Keywords: vin,decoder,vehicle,automotive
Classifier: Programming Language :: Python :: 3
Classifier: License :: OSI Approved :: MIT License
Classifier: Operating System :: OS Independent
Requires-Python: >=3.8
